rustoken-0.1.4.dist-info/METADATA
rustoken-0.1.4.dist-info/WHEEL
rustoken/__init__.py
rustoken/rustoken.cpython-313-x86_64-linux-gnu.so
rustoken-0.1.4.dist-info/RECORD
