Metadata-Version: 2.4
Name: rustoken
Version: 0.1.4
Summary: JWT library implemented in Rust for Python
Author-email: Ehsan Amiri <ehsan.amiri.prog@example.com>
Requires-Python: >=3.7
Project-URL: Homepage, https://ehs22n.github.io/rustoken/
Project-URL: Repository, https://github.com/ehs22n/rustoken
Project-URL: Documentation, https://ehs22n.github.io/rustoken/
Project-URL: Issues, https://github.com/ehs22n/rustoken/issues
